nbklu/__init__.py
nbklu/_ext.pyd
nbklu/_ext.pyi
nbklu/py.typed
nbklu/solver.py
nbklu-0.2.0.dist-info/METADATA
nbklu-0.2.0.dist-info/WHEEL
nbklu-0.2.0.dist-info/licenses/LICENSE
nbklu-0.2.0.dist-info/RECORD
