Metadata-Version: 2.4
Name: nbklu
Version: 0.2.0
Summary: Python wrapper for KLU
Author-Email: Azuk 443 <me@azuk.top>
License-Expression: BSD-3-Clause
License-File: LICENSE
Classifier: Programming Language :: Python :: 3
Classifier: Operating System :: OS Independent
Project-URL: Homepage, https://github.com/determ1ne/nbklu
Project-URL: Issues, https://github.com/determ1ne/nbklu/issues
Requires-Python: >=3.10
Requires-Dist: numpy>=2.0.0
